{
  "id": "G12-004-rejected-9",
  "task_type": "TT2_FILL",
  "title": "Үгийг хуулж бичээрэй",
  "prompt_text": "\"Зураг гоё.\" — дутуу үсгийг нөхөж бичээрэй.",
  "correct_answer": "зураг",
  "options": {
    "display_text": "зура_",
    "blank_position": 4,
    "blank_answer": "г",
    "context_word": "зураг"
  },
  "audio_url": null,
  "image_url": null,
  "primary_skill": "S2",
  "secondary_skill": null,
  "level_target": "M0",
  "error_targets": [
    "B3"
  ],
  "grade_band": [
    "G1",
    "G2"
  ],
  "difficulty": 1,
  "estimated_time_seconds": 30,
  "review_after_days": [
    1,
    3,
    7
  ],
  "lesson_slot_fit": "WARM_UP",
  "feedback_text": "Зөв хариу: зураг",
  "rejection_reasons": [
    "excess variant — already have 3 passing"
  ]
}